piehunter
