Metadata-Version: 1.0
Name: django-piehunter
Version: 0.0.3
Summary: Automatic Tastypie URL builder by way of import discovery.
Home-page: http://github.com/airtonix/django-piehunter
Author: Zenobius Jiricek
Author-email: airtonix@gmail.com
License: UNKNOWN
Platform: UNKNOWN
